glm-stubs/__init__.py
glm-stubs/__init__.pyi
glm_typing/__init__.py
glm_typing/py.typed
pyglm_typing-0.2.1.dist-info/LICENSE
pyglm_typing-0.2.1.dist-info/METADATA
pyglm_typing-0.2.1.dist-info/WHEEL
pyglm_typing-0.2.1.dist-info/top_level.txt
pyglm_typing-0.2.1.dist-info/RECORD
