Metadata-Version: 2.1
Name: pyglm-typing
Version: 0.2.1
Summary: Type stubs for PyGLM
Home-page: https://github.com/esoma/pyglm-typing
Author: Erik Soma
Author-email: stillusingirc@gmail.com
License: MIT
Platform: UNKNOWN
Classifier: License :: OSI Approved :: MIT License
Classifier: Operating System :: OS Independent
Classifier: Typing :: Typed
Classifier: Programming Language :: Python :: 3.6
Classifier: Programming Language :: Python :: 3.7
Classifier: Programming Language :: Python :: 3.8
Classifier: Programming Language :: Python :: 3.9
Classifier: Programming Language :: Python :: 3.10
Classifier: Intended Audience :: Developers
Requires-Python: >=3.6
License-File: LICENSE
